omega_wp/__init__.py
omega_wp/__main__.py
omega_wp/config.py
omega_wp/services/LoginService.py
omega_wp/services/ParametersParserService.py
omega_wp/services/PayloadService.py
omega_wp/services/ShellService.py
omega_wp/services/TerminalService.py
omega_wp/services/__init__.py
tests/__init__.py
tests/mocks.py
tests/test_login_service.py
tests/test_parameters_parser_service.py
tests/test_payload_service.py
tests/test_shell_service.py
omega_wp-2.7.dist-info/LICENSE
omega_wp-2.7.dist-info/METADATA
omega_wp-2.7.dist-info/WHEEL
omega_wp-2.7.dist-info/entry_points.txt
omega_wp-2.7.dist-info/top_level.txt
omega_wp-2.7.dist-info/RECORD
