Metadata-Version: 2.1
Name: omega-wp
Version: 2.7
Summary: From Wordpress admin to pty automatically!
Home-page: https://github.com/anthares101/omega
Author: Ángel Heredia
License: GPL-2.0
Project-URL: Release notes, https://github.com/anthares101/omega/releases
Keywords: windows macos linux shell wordpress reverse-shell tool hacking tty pty cybersecurity reverse pwntools hacktoberfest kali
Platform: UNKNOWN
Requires-Python: >=3
Requires-Dist: pwntools
Requires-Dist: requests
Requires-Dist: bs4
Requires-Dist: lxml
Provides-Extra: dev
Requires-Dist: responses ; extra == 'dev'
